uniorm/__init__.py
uniorm/database.py
uniorm/exceptions.py
uniorm/fields.py
uniorm/migrations.py
uniorm/models.py
uniorm/query.py
uniorm/utils.py
uniorm-1.0.0.dist-info/licenses/LICENSE
uniorm-1.0.0.dist-info/METADATA
uniorm-1.0.0.dist-info/WHEEL
uniorm-1.0.0.dist-info/top_level.txt
uniorm-1.0.0.dist-info/RECORD
