Metadata-Version: 2.4
Name: uniorm
Version: 1.0.0
Summary: Universal Async ORM for SQLite, MySQL, and PostgreSQL
Home-page: https://github.com/oscoderuz/uniorm
Author: oscoderuz
Author-email: oscoderuz@gmail.com
Classifier: Programming Language :: Python :: 3
Classifier: Programming Language :: Python :: 3 :: Only
Classifier: License :: OSI Approved :: MIT License
Classifier: Operating System :: OS Independent
Classifier: Framework :: AsyncIO
Classifier: Topic :: Database :: Front-Ends
Requires-Python: >=3.9
License-File: LICENSE
Provides-Extra: sqlite
Requires-Dist: aiosqlite; extra == "sqlite"
Provides-Extra: mysql
Requires-Dist: asyncmy; extra == "mysql"
Provides-Extra: postgres
Requires-Dist: psycopg[binary]; extra == "postgres"
Provides-Extra: all
Requires-Dist: aiosqlite; extra == "all"
Requires-Dist: asyncmy; extra == "all"
Requires-Dist: psycopg[binary]; extra == "all"
Dynamic: author
Dynamic: author-email
Dynamic: classifier
Dynamic: description
Dynamic: description-content-type
Dynamic: home-page
Dynamic: license-file
Dynamic: provides-extra
Dynamic: requires-python
Dynamic: summary
